{
	"main": "Необходимо пройти лабиринт. При этом на пути робота будут встречаться лужи красного и зеленого цвета. При возникновении зеленой лужи робот должен сигнализировать о ней зеленым диодом с частотой 500 мс в течение 4 секунд, красной - красным диодом с частотой 1000 мс в течение 4 секунд. Используйте для решения параллельные задачи.",
    "hints": [
        {
            "name": "Расположение моторов",
            "text": "Левый мотор - порт M3 <br/> Правый мотор - порт M4"
        },

        {
            "name": "Расположение датчиков",
            "text": "Инфракрасный датчик, смотрящий направо - порт A1 <br> Инфракрасный датчик, смотрящий вниз - порт A2 "
        }
    ]
}
